ductworks
