Metadata-Version: 1.1
Name: ductworks
Version: 0.0.1a3
Summary: A simple IPC library for less simple situations.
Home-page: https://bitbucket.org/rpcope1/ductworks
Author: Robert Cope
Author-email: rpcope1@gmail.com
License: UNKNOWN
Platform: UNKNOWN
Classifier: Development Status :: 2 - Pre-Alpha
Classifier: Topic :: Software Development :: Libraries :: Python Modules
Classifier: Topic :: System :: Networking
Classifier: License :: OSI Approved :: BSD License
